table_permissions/__init__.py
table_permissions/admin.py
table_permissions/app_settings.py
table_permissions/helpers.py
table_permissions/locale/ar/LC_MESSAGES/django.po
table_permissions/static/table_permissions/table_permissions.js
table_permissions/templates/table_permissions/admin/table_permissions.html
table_permissions/widgets.py
django_table_permissions-0.1.0b3.dist-info/LICENSE
django_table_permissions-0.1.0b3.dist-info/METADATA
django_table_permissions-0.1.0b3.dist-info/WHEEL
django_table_permissions-0.1.0b3.dist-info/RECORD
