Metadata-Version: 2.1
Name: django-table-permissions
Version: 0.1.0b3
Summary: Display django permissions in a user friendly, translatable and customizable widget.
License: BSD-2
Keywords: django,admin,permissions
Author: Dharwin Perez
Author-email: dharwin@codelovers.club
Requires-Python: >=3.10,<4.0
Classifier: License :: Other/Proprietary License
Classifier: Programming Language :: Python :: 3
Classifier: Programming Language :: Python :: 3.10
Classifier: Programming Language :: Python :: 3.11
Classifier: Programming Language :: Python :: 3.12
Requires-Dist: django (>=4.2.10,<5.0.0)
